{
  "project_info": {
    "project_number": "423432630363",
    "firebase_url": "https://detectivegame-1053a.firebaseio.com",
    "project_id": "detectivegame-1053a",
    "storage_bucket": "detectivegame-1053a.appspot.com"
  },
  "client": [
    {
      "client_info": {
        "mobilesdk_app_id": "1:423432630363:android:a21cff7b57e3f45046cf7e",
        "android_client_info": {
          "package_name": "de.hpi3d.gamepgrog.trap"
        }
      },
      "oauth_client": [
        {
          "client_id": "423432630363-qsbduh2hbc5018njonljtgcmpm1uqe8a.apps.googleusercontent.com",
          "client_type": 3
        }
      ],
      "api_key": [
        {
          "current_key": "AIzaSyAuWdzoK2RJWbQoMlNsa-Zqmb62B31ywhU"
        }
      ],
      "services": {
        "appinvite_service": {
          "other_platform_oauth_client": [
            {
              "client_id": "423432630363-qsbduh2hbc5018njonljtgcmpm1uqe8a.apps.googleusercontent.com",
              "client_type": 3
            }
          ]
        }
      }
    }
  ],
  "configuration_version": "1"
}